README.txt
setup.cfg
setup.py
docs/HISTORY.txt
docs/LICENSE.GPL
docs/LICENSE.txt
docs/MANUAL.txt
raptus/__init__.py
raptus.article.contentflow.egg-info/PKG-INFO
raptus.article.contentflow.egg-info/SOURCES.txt
raptus.article.contentflow.egg-info/dependency_links.txt
raptus.article.contentflow.egg-info/entry_points.txt
raptus.article.contentflow.egg-info/namespace_packages.txt
raptus.article.contentflow.egg-info/not-zip-safe
raptus.article.contentflow.egg-info/requires.txt
raptus.article.contentflow.egg-info/top_level.txt
raptus/article/__init__.py
raptus/article/contentflow/__init__.py
raptus/article/contentflow/configure.zcml
raptus/article/contentflow/browser/__init__.py
raptus/article/contentflow/browser/configure.zcml
raptus/article/contentflow/browser/contentflow.gif
raptus/article/contentflow/browser/contentflow.py
raptus/article/contentflow/browser/contentflow_teaser.gif
raptus/article/contentflow/i18n/raptus.article-de.po
raptus/article/contentflow/i18n/raptus.article-fr.po
raptus/article/contentflow/i18n/raptus.article.pot
raptus/article/contentflow/profiles/default/metadata.xml
raptus/article/contentflow/profiles/default/propertiestool.xml
raptus/article/contentflow/profiles/default/viewlets.xml