Metadata-Version: 1.0
Name: raptus.article.contentflow
Version: 2.0b4
Summary: Provides a content flow component
Home-page: http://raptus.com
Author: Raptus AG
Author-email: dev@raptus.com
License: GPL
Platform: UNKNOWN
Classifier: Programming Language :: Python
Classifier: Topic :: Software Development :: Libraries :: Python Modules
